[
  {
    "path": "/Users/bene/dev/sqip/demo/public/original/aaron-burden-151465-unsplash.jpg",
    "filename": "aaron-burden-151465-unsplash",
    "results": [
      {
        "variantName": "thumbnail",
        "name": "aaron-burden-151465-unsplash-thumbnail.jpg",
        "dist": "/Users/bene/dev/sqip/demo/public/processed/aaron-burden-151465-unsplash-thumbnail.jpg",
        "sizes": {
          "originalBytes": 38496,
          "originalHuman": "38.5 kB",
          "gzipBytes": 17323,
          "gzipHuman": "17.3 kB",
          "brotliBytes": 17058,
          "brotliHuman": "17.1 kB"
        },
        "dimensions": {
          "width": 300,
          "height": 225,
          "ratio": "4:3"
        },
        "processTime": [
          0,
          118711340
        ]
      },
      {
        "variantName": "lqip",
        "name": "aaron-burden-151465-unsplash-lqip.jpg",
        "dist": "/Users/bene/dev/sqip/demo/public/processed/aaron-burden-151465-unsplash-lqip.jpg",
        "sizes": {
          "originalBytes": 1247,
          "originalHuman": "1.25 kB",
          "gzipBytes": 796,
          "gzipHuman": "796 B",
          "brotliBytes": 773,
          "brotliHuman": "773 B"
        },
        "dimensions": {
          "width": 10,
          "height": 8,
          "ratio": "5:4"
        },
        "processTime": [
          0,
          909687398
        ]
      },
      {
        "variantName": "sqip-legacy",
        "name": "aaron-burden-151465-unsplash-sqip-legacy.svg",
        "dist": "/Users/bene/dev/sqip/demo/public/processed/aaron-burden-151465-unsplash-sqip-legacy.svg",
        "sizes": {
          "originalBytes": 1282,
          "originalHuman": "1.28 kB",
          "gzipBytes": 760,
          "gzipHuman": "760 B",
          "brotliBytes": 757,
          "brotliHuman": "757 B"
        },
        "dimensions": {
          "width": 2000,
          "height": 1500,
          "ratio": "4:3"
        },
        "processTime": [
          2,
          293228559
        ]
      },
      {
        "variantName": "sqip",
        "name": "aaron-burden-151465-unsplash-sqip.svg",
        "dist": "/Users/bene/dev/sqip/demo/public/processed/aaron-burden-151465-unsplash-sqip.svg",
        "sizes": {
          "originalBytes": 1048,
          "originalHuman": "1.05 kB",
          "gzipBytes": 538,
          "gzipHuman": "538 B",
          "brotliBytes": 480,
          "brotliHuman": "480 B"
        },
        "dimensions": {
          "width": 300,
          "height": 225,
          "ratio": "4:3"
        },
        "processTime": [
          3,
          487209476
        ]
      },
      {
        "variantName": "sqip-pixels",
        "name": "aaron-burden-151465-unsplash-sqip-pixels.svg",
        "dist": "/Users/bene/dev/sqip/demo/public/processed/aaron-burden-151465-unsplash-sqip-pixels.svg",
        "sizes": {
          "originalBytes": 2661,
          "originalHuman": "2.66 kB",
          "gzipBytes": 569,
          "gzipHuman": "569 B",
          "brotliBytes": 410,
          "brotliHuman": "410 B"
        },
        "dimensions": {
          "width": 800,
          "height": 600,
          "ratio": "4:3"
        },
        "processTime": [
          1,
          643315321
        ]
      },
      {
        "variantName": "sqip-art",
        "name": "aaron-burden-151465-unsplash-sqip-art.svg",
        "dist": "/Users/bene/dev/sqip/demo/public/processed/aaron-burden-151465-unsplash-sqip-art.svg",
        "sizes": {
          "originalBytes": 3305,
          "originalHuman": "3.31 kB",
          "gzipBytes": 1219,
          "gzipHuman": "1.22 kB",
          "brotliBytes": 1092,
          "brotliHuman": "1.09 kB"
        },
        "dimensions": {
          "width": 300,
          "height": 225,
          "ratio": "4:3"
        },
        "processTime": [
          6,
          760873902
        ]
      }
    ],
    "dimensions": {
      "width": 2000,
      "height": 1500,
      "ratio": "4:3"
    }
  },
  {
    "path": "/Users/bene/dev/sqip/demo/public/original/anthony-esau-173126-unsplash.jpg",
    "filename": "anthony-esau-173126-unsplash",
    "results": [
      {
        "variantName": "thumbnail",
        "name": "anthony-esau-173126-unsplash-thumbnail.jpg",
        "dist": "/Users/bene/dev/sqip/demo/public/processed/anthony-esau-173126-unsplash-thumbnail.jpg",
        "sizes": {
          "originalBytes": 23902,
          "originalHuman": "23.9 kB",
          "gzipBytes": 10984,
          "gzipHuman": "11 kB",
          "brotliBytes": 10863,
          "brotliHuman": "10.9 kB"
        },
        "dimensions": {
          "width": 300,
          "height": 225,
          "ratio": "4:3"
        },
        "processTime": [
          0,
          83713816
        ]
      },
      {
        "variantName": "lqip",
        "name": "anthony-esau-173126-unsplash-lqip.jpg",
        "dist": "/Users/bene/dev/sqip/demo/public/processed/anthony-esau-173126-unsplash-lqip.jpg",
        "sizes": {
          "originalBytes": 1247,
          "originalHuman": "1.25 kB",
          "gzipBytes": 795,
          "gzipHuman": "795 B",
          "brotliBytes": 772,
          "brotliHuman": "772 B"
        },
        "dimensions": {
          "width": 10,
          "height": 8,
          "ratio": "5:4"
        },
        "processTime": [
          0,
          580641473
        ]
      },
      {
        "variantName": "sqip-legacy",
        "name": "anthony-esau-173126-unsplash-sqip-legacy.svg",
        "dist": "/Users/bene/dev/sqip/demo/public/processed/anthony-esau-173126-unsplash-sqip-legacy.svg",
        "sizes": {
          "originalBytes": 1402,
          "originalHuman": "1.4 kB",
          "gzipBytes": 783,
          "gzipHuman": "783 B",
          "brotliBytes": 786,
          "brotliHuman": "786 B"
        },
        "dimensions": {
          "width": 2000,
          "height": 1500,
          "ratio": "4:3"
        },
        "processTime": [
          2,
          816058645
        ]
      },
      {
        "variantName": "sqip",
        "name": "anthony-esau-173126-unsplash-sqip.svg",
        "dist": "/Users/bene/dev/sqip/demo/public/processed/anthony-esau-173126-unsplash-sqip.svg",
        "sizes": {
          "originalBytes": 1137,
          "originalHuman": "1.14 kB",
          "gzipBytes": 548,
          "gzipHuman": "548 B",
          "brotliBytes": 491,
          "brotliHuman": "491 B"
        },
        "dimensions": {
          "width": 300,
          "height": 225,
          "ratio": "4:3"
        },
        "processTime": [
          3,
          257144095
        ]
      },
      {
        "variantName": "sqip-pixels",
        "name": "anthony-esau-173126-unsplash-sqip-pixels.svg",
        "dist": "/Users/bene/dev/sqip/demo/public/processed/anthony-esau-173126-unsplash-sqip-pixels.svg",
        "sizes": {
          "originalBytes": 2661,
          "originalHuman": "2.66 kB",
          "gzipBytes": 565,
          "gzipHuman": "565 B",
          "brotliBytes": 407,
          "brotliHuman": "407 B"
        },
        "dimensions": {
          "width": 800,
          "height": 600,
          "ratio": "4:3"
        },
        "processTime": [
          0,
          974652501
        ]
      },
      {
        "variantName": "sqip-art",
        "name": "anthony-esau-173126-unsplash-sqip-art.svg",
        "dist": "/Users/bene/dev/sqip/demo/public/processed/anthony-esau-173126-unsplash-sqip-art.svg",
        "sizes": {
          "originalBytes": 3305,
          "originalHuman": "3.31 kB",
          "gzipBytes": 1245,
          "gzipHuman": "1.25 kB",
          "brotliBytes": 1104,
          "brotliHuman": "1.1 kB"
        },
        "dimensions": {
          "width": 300,
          "height": 225,
          "ratio": "4:3"
        },
        "processTime": [
          8,
          511901368
        ]
      }
    ],
    "dimensions": {
      "width": 2000,
      "height": 1500,
      "ratio": "4:3"
    }
  },
  {
    "path": "/Users/bene/dev/sqip/demo/public/original/aron-visuals-974734-unsplash.jpg",
    "filename": "aron-visuals-974734-unsplash",
    "results": [
      {
        "variantName": "thumbnail",
        "name": "aron-visuals-974734-unsplash-thumbnail.jpg",
        "dist": "/Users/bene/dev/sqip/demo/public/processed/aron-visuals-974734-unsplash-thumbnail.jpg",
        "sizes": {
          "originalBytes": 22225,
          "originalHuman": "22.2 kB",
          "gzipBytes": 10090,
          "gzipHuman": "10.1 kB",
          "brotliBytes": 9952,
          "brotliHuman": "9.95 kB"
        },
        "dimensions": {
          "width": 300,
          "height": 375,
          "ratio": "5:4"
        },
        "processTime": [
          0,
          119576338
        ]
      },
      {
        "variantName": "lqip",
        "name": "aron-visuals-974734-unsplash-lqip.jpg",
        "dist": "/Users/bene/dev/sqip/demo/public/processed/aron-visuals-974734-unsplash-lqip.jpg",
        "sizes": {
          "originalBytes": 1407,
          "originalHuman": "1.41 kB",
          "gzipBytes": 917,
          "gzipHuman": "917 B",
          "brotliBytes": 895,
          "brotliHuman": "895 B"
        },
        "dimensions": {
          "width": 10,
          "height": 13,
          "ratio": "13:10"
        },
        "processTime": [
          1,
          266571031
        ]
      },
      {
        "variantName": "sqip-legacy",
        "name": "aron-visuals-974734-unsplash-sqip-legacy.svg",
        "dist": "/Users/bene/dev/sqip/demo/public/processed/aron-visuals-974734-unsplash-sqip-legacy.svg",
        "sizes": {
          "originalBytes": 1262,
          "originalHuman": "1.26 kB",
          "gzipBytes": 761,
          "gzipHuman": "761 B",
          "brotliBytes": 754,
          "brotliHuman": "754 B"
        },
        "dimensions": {
          "width": 2000,
          "height": 2500,
          "ratio": "5:4"
        },
        "processTime": [
          6,
          892031901
        ]
      },
      {
        "variantName": "sqip",
        "name": "aron-visuals-974734-unsplash-sqip.svg",
        "dist": "/Users/bene/dev/sqip/demo/public/processed/aron-visuals-974734-unsplash-sqip.svg",
        "sizes": {
          "originalBytes": 1084,
          "originalHuman": "1.08 kB",
          "gzipBytes": 533,
          "gzipHuman": "533 B",
          "brotliBytes": 473,
          "brotliHuman": "473 B"
        },
        "dimensions": {
          "width": 300,
          "height": 375,
          "ratio": "5:4"
        },
        "processTime": [
          6,
          696357394
        ]
      },
      {
        "variantName": "sqip-pixels",
        "name": "aron-visuals-974734-unsplash-sqip-pixels.svg",
        "dist": "/Users/bene/dev/sqip/demo/public/processed/aron-visuals-974734-unsplash-sqip-pixels.svg",
        "sizes": {
          "originalBytes": 4374,
          "originalHuman": "4.37 kB",
          "gzipBytes": 796,
          "gzipHuman": "796 B",
          "brotliBytes": 546,
          "brotliHuman": "546 B"
        },
        "dimensions": {
          "width": 800,
          "height": 1000,
          "ratio": "5:4"
        },
        "processTime": [
          1,
          624809618
        ]
      },
      {
        "variantName": "sqip-art",
        "name": "aron-visuals-974734-unsplash-sqip-art.svg",
        "dist": "/Users/bene/dev/sqip/demo/public/processed/aron-visuals-974734-unsplash-sqip-art.svg",
        "sizes": {
          "originalBytes": 3381,
          "originalHuman": "3.38 kB",
          "gzipBytes": 1252,
          "gzipHuman": "1.25 kB",
          "brotliBytes": 1118,
          "brotliHuman": "1.12 kB"
        },
        "dimensions": {
          "width": 298,
          "height": 375,
          "ratio": "375:298"
        },
        "processTime": [
          11,
          842652557
        ]
      }
    ],
    "dimensions": {
      "width": 2000,
      "height": 2500,
      "ratio": "5:4"
    }
  },
  {
    "path": "/Users/bene/dev/sqip/demo/public/original/beach.jpg",
    "filename": "beach",
    "results": [
      {
        "variantName": "thumbnail",
        "name": "beach-thumbnail.jpg",
        "dist": "/Users/bene/dev/sqip/demo/public/processed/beach-thumbnail.jpg",
        "sizes": {
          "originalBytes": 13749,
          "originalHuman": "13.7 kB",
          "gzipBytes": 6197,
          "gzipHuman": "6.2 kB",
          "brotliBytes": 6134,
          "brotliHuman": "6.13 kB"
        },
        "dimensions": {
          "width": 300,
          "height": 188,
          "ratio": "75:47"
        },
        "processTime": [
          0,
          53694718
        ]
      },
      {
        "variantName": "lqip",
        "name": "beach-lqip.jpg",
        "dist": "/Users/bene/dev/sqip/demo/public/processed/beach-lqip.jpg",
        "sizes": {
          "originalBytes": 1263,
          "originalHuman": "1.26 kB",
          "gzipBytes": 805,
          "gzipHuman": "805 B",
          "brotliBytes": 784,
          "brotliHuman": "784 B"
        },
        "dimensions": {
          "width": 10,
          "height": 6,
          "ratio": "5:3"
        },
        "processTime": [
          0,
          249361164
        ]
      },
      {
        "variantName": "sqip-legacy",
        "name": "beach-sqip-legacy.svg",
        "dist": "/Users/bene/dev/sqip/demo/public/processed/beach-sqip-legacy.svg",
        "sizes": {
          "originalBytes": 1266,
          "originalHuman": "1.27 kB",
          "gzipBytes": 742,
          "gzipHuman": "742 B",
          "brotliBytes": 726,
          "brotliHuman": "726 B"
        },
        "dimensions": {
          "width": 1024,
          "height": 640,
          "ratio": "8:5"
        },
        "processTime": [
          2,
          989908315
        ]
      },
      {
        "variantName": "sqip",
        "name": "beach-sqip.svg",
        "dist": "/Users/bene/dev/sqip/demo/public/processed/beach-sqip.svg",
        "sizes": {
          "originalBytes": 1069,
          "originalHuman": "1.07 kB",
          "gzipBytes": 541,
          "gzipHuman": "541 B",
          "brotliBytes": 476,
          "brotliHuman": "476 B"
        },
        "dimensions": {
          "width": 300,
          "height": 188,
          "ratio": "75:47"
        },
        "processTime": [
          2,
          970717501
        ]
      },
      {
        "variantName": "sqip-pixels",
        "name": "beach-sqip-pixels.svg",
        "dist": "/Users/bene/dev/sqip/demo/public/processed/beach-sqip-pixels.svg",
        "sizes": {
          "originalBytes": 2233,
          "originalHuman": "2.23 kB",
          "gzipBytes": 505,
          "gzipHuman": "505 B",
          "brotliBytes": 364,
          "brotliHuman": "364 B"
        },
        "dimensions": {
          "width": 800,
          "height": 500,
          "ratio": "8:5"
        },
        "processTime": [
          0,
          202068819
        ]
      },
      {
        "variantName": "sqip-art",
        "name": "beach-sqip-art.svg",
        "dist": "/Users/bene/dev/sqip/demo/public/processed/beach-sqip-art.svg",
        "sizes": {
          "originalBytes": 3308,
          "originalHuman": "3.31 kB",
          "gzipBytes": 1231,
          "gzipHuman": "1.23 kB",
          "brotliBytes": 1094,
          "brotliHuman": "1.09 kB"
        },
        "dimensions": {
          "width": 300,
          "height": 187,
          "ratio": "300:187"
        },
        "processTime": [
          11,
          39262761
        ]
      }
    ],
    "dimensions": {
      "width": 1024,
      "height": 640,
      "ratio": "8:5"
    }
  },
  {
    "path": "/Users/bene/dev/sqip/demo/public/original/charles-550068-unsplash.jpg",
    "filename": "charles-550068-unsplash",
    "results": [
      {
        "variantName": "thumbnail",
        "name": "charles-550068-unsplash-thumbnail.jpg",
        "dist": "/Users/bene/dev/sqip/demo/public/processed/charles-550068-unsplash-thumbnail.jpg",
        "sizes": {
          "originalBytes": 27813,
          "originalHuman": "27.8 kB",
          "gzipBytes": 12720,
          "gzipHuman": "12.7 kB",
          "brotliBytes": 12520,
          "brotliHuman": "12.5 kB"
        },
        "dimensions": {
          "width": 300,
          "height": 418,
          "ratio": "209:150"
        },
        "processTime": [
          0,
          141439214
        ]
      },
      {
        "variantName": "lqip",
        "name": "charles-550068-unsplash-lqip.jpg",
        "dist": "/Users/bene/dev/sqip/demo/public/processed/charles-550068-unsplash-lqip.jpg",
        "sizes": {
          "originalBytes": 1431,
          "originalHuman": "1.43 kB",
          "gzipBytes": 934,
          "gzipHuman": "934 B",
          "brotliBytes": 919,
          "brotliHuman": "919 B"
        },
        "dimensions": {
          "width": 10,
          "height": 14,
          "ratio": "7:5"
        },
        "processTime": [
          1,
          441698545
        ]
      },
      {
        "variantName": "sqip-legacy",
        "name": "charles-550068-unsplash-sqip-legacy.svg",
        "dist": "/Users/bene/dev/sqip/demo/public/processed/charles-550068-unsplash-sqip-legacy.svg",
        "sizes": {
          "originalBytes": 1110,
          "originalHuman": "1.11 kB",
          "gzipBytes": 712,
          "gzipHuman": "712 B",
          "brotliBytes": 704,
          "brotliHuman": "704 B"
        },
        "dimensions": {
          "width": 2000,
          "height": 2785,
          "ratio": "557:400"
        },
        "processTime": [
          6,
          331423938
        ]
      },
      {
        "variantName": "sqip",
        "name": "charles-550068-unsplash-sqip.svg",
        "dist": "/Users/bene/dev/sqip/demo/public/processed/charles-550068-unsplash-sqip.svg",
        "sizes": {
          "originalBytes": 875,
          "originalHuman": "875 B",
          "gzipBytes": 492,
          "gzipHuman": "492 B",
          "brotliBytes": 441,
          "brotliHuman": "441 B"
        },
        "dimensions": {
          "width": 300,
          "height": 418,
          "ratio": "209:150"
        },
        "processTime": [
          5,
          922586110
        ]
      },
      {
        "variantName": "sqip-pixels",
        "name": "charles-550068-unsplash-sqip-pixels.svg",
        "dist": "/Users/bene/dev/sqip/demo/public/processed/charles-550068-unsplash-sqip-pixels.svg",
        "sizes": {
          "originalBytes": 4810,
          "originalHuman": "4.81 kB",
          "gzipBytes": 863,
          "gzipHuman": "863 B",
          "brotliBytes": 604,
          "brotliHuman": "604 B"
        },
        "dimensions": {
          "width": 800,
          "height": 1100,
          "ratio": "11:8"
        },
        "processTime": [
          1,
          233219918
        ]
      },
      {
        "variantName": "sqip-art",
        "name": "charles-550068-unsplash-sqip-art.svg",
        "dist": "/Users/bene/dev/sqip/demo/public/processed/charles-550068-unsplash-sqip-art.svg",
        "sizes": {
          "originalBytes": 3229,
          "originalHuman": "3.23 kB",
          "gzipBytes": 1218,
          "gzipHuman": "1.22 kB",
          "brotliBytes": 1094,
          "brotliHuman": "1.09 kB"
        },
        "dimensions": {
          "width": 300,
          "height": 418,
          "ratio": "209:150"
        },
        "processTime": [
          15,
          306887983
        ]
      }
    ],
    "dimensions": {
      "width": 2000,
      "height": 2785,
      "ratio": "557:400"
    }
  },
  {
    "path": "/Users/bene/dev/sqip/demo/public/original/eric-marty-780304-unsplash.jpg",
    "filename": "eric-marty-780304-unsplash",
    "results": [
      {
        "variantName": "thumbnail",
        "name": "eric-marty-780304-unsplash-thumbnail.jpg",
        "dist": "/Users/bene/dev/sqip/demo/public/processed/eric-marty-780304-unsplash-thumbnail.jpg",
        "sizes": {
          "originalBytes": 28852,
          "originalHuman": "28.9 kB",
          "gzipBytes": 13191,
          "gzipHuman": "13.2 kB",
          "brotliBytes": 13057,
          "brotliHuman": "13.1 kB"
        },
        "dimensions": {
          "width": 300,
          "height": 300,
          "ratio": "1:1"
        },
        "processTime": [
          0,
          150305237
        ]
      },
      {
        "variantName": "lqip",
        "name": "eric-marty-780304-unsplash-lqip.jpg",
        "dist": "/Users/bene/dev/sqip/demo/public/processed/eric-marty-780304-unsplash-lqip.jpg",
        "sizes": {
          "originalBytes": 1443,
          "originalHuman": "1.44 kB",
          "gzipBytes": 946,
          "gzipHuman": "946 B",
          "brotliBytes": 929,
          "brotliHuman": "929 B"
        },
        "dimensions": {
          "width": 10,
          "height": 10,
          "ratio": "1:1"
        },
        "processTime": [
          3,
          79509772
        ]
      },
      {
        "variantName": "sqip-legacy",
        "name": "eric-marty-780304-unsplash-sqip-legacy.svg",
        "dist": "/Users/bene/dev/sqip/demo/public/processed/eric-marty-780304-unsplash-sqip-legacy.svg",
        "sizes": {
          "originalBytes": 1190,
          "originalHuman": "1.19 kB",
          "gzipBytes": 739,
          "gzipHuman": "739 B",
          "brotliBytes": 730,
          "brotliHuman": "730 B"
        },
        "dimensions": {
          "width": 2000,
          "height": 2000,
          "ratio": "1:1"
        },
        "processTime": [
          10,
          788324397
        ]
      },
      {
        "variantName": "sqip",
        "name": "eric-marty-780304-unsplash-sqip.svg",
        "dist": "/Users/bene/dev/sqip/demo/public/processed/eric-marty-780304-unsplash-sqip.svg",
        "sizes": {
          "originalBytes": 1099,
          "originalHuman": "1.1 kB",
          "gzipBytes": 545,
          "gzipHuman": "545 B",
          "brotliBytes": 485,
          "brotliHuman": "485 B"
        },
        "dimensions": {
          "width": 300,
          "height": 300,
          "ratio": "1:1"
        },
        "processTime": [
          8,
          52564372
        ]
      },
      {
        "variantName": "sqip-pixels",
        "name": "eric-marty-780304-unsplash-sqip-pixels.svg",
        "dist": "/Users/bene/dev/sqip/demo/public/processed/eric-marty-780304-unsplash-sqip-pixels.svg",
        "sizes": {
          "originalBytes": 3517,
          "originalHuman": "3.52 kB",
          "gzipBytes": 682,
          "gzipHuman": "682 B",
          "brotliBytes": 485,
          "brotliHuman": "485 B"
        },
        "dimensions": {
          "width": 800,
          "height": 800,
          "ratio": "1:1"
        },
        "processTime": [
          1,
          170039279
        ]
      },
      {
        "variantName": "sqip-art",
        "name": "eric-marty-780304-unsplash-sqip-art.svg",
        "dist": "/Users/bene/dev/sqip/demo/public/processed/eric-marty-780304-unsplash-sqip-art.svg",
        "sizes": {
          "originalBytes": 3329,
          "originalHuman": "3.33 kB",
          "gzipBytes": 1236,
          "gzipHuman": "1.24 kB",
          "brotliBytes": 1117,
          "brotliHuman": "1.12 kB"
        },
        "dimensions": {
          "width": 300,
          "height": 300,
          "ratio": "1:1"
        },
        "processTime": [
          15,
          460411888
        ]
      }
    ],
    "dimensions": {
      "width": 2000,
      "height": 2000,
      "ratio": "1:1"
    }
  },
  {
    "path": "/Users/bene/dev/sqip/demo/public/original/ian-dooley-298769-unsplash.jpg",
    "filename": "ian-dooley-298769-unsplash",
    "results": [
      {
        "variantName": "thumbnail",
        "name": "ian-dooley-298769-unsplash-thumbnail.jpg",
        "dist": "/Users/bene/dev/sqip/demo/public/processed/ian-dooley-298769-unsplash-thumbnail.jpg",
        "sizes": {
          "originalBytes": 8648,
          "originalHuman": "8.65 kB",
          "gzipBytes": 4210,
          "gzipHuman": "4.21 kB",
          "brotliBytes": 4120,
          "brotliHuman": "4.12 kB"
        },
        "dimensions": {
          "width": 300,
          "height": 450,
          "ratio": "3:2"
        },
        "processTime": [
          0,
          98490567
        ]
      },
      {
        "variantName": "lqip",
        "name": "ian-dooley-298769-unsplash-lqip.jpg",
        "dist": "/Users/bene/dev/sqip/demo/public/processed/ian-dooley-298769-unsplash-lqip.jpg",
        "sizes": {
          "originalBytes": 1247,
          "originalHuman": "1.25 kB",
          "gzipBytes": 797,
          "gzipHuman": "797 B",
          "brotliBytes": 777,
          "brotliHuman": "777 B"
        },
        "dimensions": {
          "width": 10,
          "height": 15,
          "ratio": "3:2"
        },
        "processTime": [
          0,
          981146102
        ]
      },
      {
        "variantName": "sqip-legacy",
        "name": "ian-dooley-298769-unsplash-sqip-legacy.svg",
        "dist": "/Users/bene/dev/sqip/demo/public/processed/ian-dooley-298769-unsplash-sqip-legacy.svg",
        "sizes": {
          "originalBytes": 1086,
          "originalHuman": "1.09 kB",
          "gzipBytes": 718,
          "gzipHuman": "718 B",
          "brotliBytes": 708,
          "brotliHuman": "708 B"
        },
        "dimensions": {
          "width": 2000,
          "height": 3000,
          "ratio": "3:2"
        },
        "processTime": [
          2,
          855648825
        ]
      },
      {
        "variantName": "sqip",
        "name": "ian-dooley-298769-unsplash-sqip.svg",
        "dist": "/Users/bene/dev/sqip/demo/public/processed/ian-dooley-298769-unsplash-sqip.svg",
        "sizes": {
          "originalBytes": 909,
          "originalHuman": "909 B",
          "gzipBytes": 505,
          "gzipHuman": "505 B",
          "brotliBytes": 456,
          "brotliHuman": "456 B"
        },
        "dimensions": {
          "width": 300,
          "height": 450,
          "ratio": "3:2"
        },
        "processTime": [
          3,
          794703261
        ]
      },
      {
        "variantName": "sqip-pixels",
        "name": "ian-dooley-298769-unsplash-sqip-pixels.svg",
        "dist": "/Users/bene/dev/sqip/demo/public/processed/ian-dooley-298769-unsplash-sqip-pixels.svg",
        "sizes": {
          "originalBytes": 5068,
          "originalHuman": "5.07 kB",
          "gzipBytes": 825,
          "gzipHuman": "825 B",
          "brotliBytes": 589,
          "brotliHuman": "589 B"
        },
        "dimensions": {
          "width": 800,
          "height": 1200,
          "ratio": "3:2"
        },
        "processTime": [
          1,
          255339157
        ]
      },
      {
        "variantName": "sqip-art",
        "name": "ian-dooley-298769-unsplash-sqip-art.svg",
        "dist": "/Users/bene/dev/sqip/demo/public/processed/ian-dooley-298769-unsplash-sqip-art.svg",
        "sizes": {
          "originalBytes": 3352,
          "originalHuman": "3.35 kB",
          "gzipBytes": 1216,
          "gzipHuman": "1.22 kB",
          "brotliBytes": 1115,
          "brotliHuman": "1.11 kB"
        },
        "dimensions": {
          "width": 298,
          "height": 450,
          "ratio": "225:149"
        },
        "processTime": [
          10,
          133544166
        ]
      }
    ],
    "dimensions": {
      "width": 2000,
      "height": 3000,
      "ratio": "3:2"
    }
  },
  {
    "path": "/Users/bene/dev/sqip/demo/public/original/meric-dagli-487815-unsplash.jpg",
    "filename": "meric-dagli-487815-unsplash",
    "results": [
      {
        "variantName": "thumbnail",
        "name": "meric-dagli-487815-unsplash-thumbnail.jpg",
        "dist": "/Users/bene/dev/sqip/demo/public/processed/meric-dagli-487815-unsplash-thumbnail.jpg",
        "sizes": {
          "originalBytes": 42916,
          "originalHuman": "42.9 kB",
          "gzipBytes": 19298,
          "gzipHuman": "19.3 kB",
          "brotliBytes": 18980,
          "brotliHuman": "19 kB"
        },
        "dimensions": {
          "width": 300,
          "height": 450,
          "ratio": "3:2"
        },
        "processTime": [
          0,
          166013368
        ]
      },
      {
        "variantName": "lqip",
        "name": "meric-dagli-487815-unsplash-lqip.jpg",
        "dist": "/Users/bene/dev/sqip/demo/public/processed/meric-dagli-487815-unsplash-lqip.jpg",
        "sizes": {
          "originalBytes": 1763,
          "originalHuman": "1.76 kB",
          "gzipBytes": 1187,
          "gzipHuman": "1.19 kB",
          "brotliBytes": 1167,
          "brotliHuman": "1.17 kB"
        },
        "dimensions": {
          "width": 10,
          "height": 15,
          "ratio": "3:2"
        },
        "processTime": [
          1,
          270791977
        ]
      },
      {
        "variantName": "sqip-legacy",
        "name": "meric-dagli-487815-unsplash-sqip-legacy.svg",
        "dist": "/Users/bene/dev/sqip/demo/public/processed/meric-dagli-487815-unsplash-sqip-legacy.svg",
        "sizes": {
          "originalBytes": 1270,
          "originalHuman": "1.27 kB",
          "gzipBytes": 722,
          "gzipHuman": "722 B",
          "brotliBytes": 702,
          "brotliHuman": "702 B"
        },
        "dimensions": {
          "width": 2000,
          "height": 3000,
          "ratio": "3:2"
        },
        "processTime": [
          3,
          831080045
        ]
      },
      {
        "variantName": "sqip",
        "name": "meric-dagli-487815-unsplash-sqip.svg",
        "dist": "/Users/bene/dev/sqip/demo/public/processed/meric-dagli-487815-unsplash-sqip.svg",
        "sizes": {
          "originalBytes": 1132,
          "originalHuman": "1.13 kB",
          "gzipBytes": 549,
          "gzipHuman": "549 B",
          "brotliBytes": 485,
          "brotliHuman": "485 B"
        },
        "dimensions": {
          "width": 300,
          "height": 450,
          "ratio": "3:2"
        },
        "processTime": [
          4,
          939416783
        ]
      },
      {
        "variantName": "sqip-pixels",
        "name": "meric-dagli-487815-unsplash-sqip-pixels.svg",
        "dist": "/Users/bene/dev/sqip/demo/public/processed/meric-dagli-487815-unsplash-sqip-pixels.svg",
        "sizes": {
          "originalBytes": 5243,
          "originalHuman": "5.24 kB",
          "gzipBytes": 944,
          "gzipHuman": "944 B",
          "brotliBytes": 634,
          "brotliHuman": "634 B"
        },
        "dimensions": {
          "width": 800,
          "height": 1200,
          "ratio": "3:2"
        },
        "processTime": [
          1,
          394982727
        ]
      },
      {
        "variantName": "sqip-art",
        "name": "meric-dagli-487815-unsplash-sqip-art.svg",
        "dist": "/Users/bene/dev/sqip/demo/public/processed/meric-dagli-487815-unsplash-sqip-art.svg",
        "sizes": {
          "originalBytes": 3396,
          "originalHuman": "3.4 kB",
          "gzipBytes": 1280,
          "gzipHuman": "1.28 kB",
          "brotliBytes": 1144,
          "brotliHuman": "1.14 kB"
        },
        "dimensions": {
          "width": 298,
          "height": 450,
          "ratio": "225:149"
        },
        "processTime": [
          9,
          765905086
        ]
      }
    ],
    "dimensions": {
      "width": 2000,
      "height": 3000,
      "ratio": "3:2"
    }
  },
  {
    "path": "/Users/bene/dev/sqip/demo/public/original/mona-lisa.jpg",
    "filename": "mona-lisa",
    "results": [
      {
        "variantName": "thumbnail",
        "name": "mona-lisa-thumbnail.jpg",
        "dist": "/Users/bene/dev/sqip/demo/public/processed/mona-lisa-thumbnail.jpg",
        "sizes": {
          "originalBytes": 36279,
          "originalHuman": "36.3 kB",
          "gzipBytes": 16449,
          "gzipHuman": "16.4 kB",
          "brotliBytes": 16239,
          "brotliHuman": "16.2 kB"
        },
        "dimensions": {
          "width": 300,
          "height": 447,
          "ratio": "149:100"
        },
        "processTime": [
          0,
          103189970
        ]
      },
      {
        "variantName": "lqip",
        "name": "mona-lisa-lqip.jpg",
        "dist": "/Users/bene/dev/sqip/demo/public/processed/mona-lisa-lqip.jpg",
        "sizes": {
          "originalBytes": 1587,
          "originalHuman": "1.59 kB",
          "gzipBytes": 1056,
          "gzipHuman": "1.06 kB",
          "brotliBytes": 1029,
          "brotliHuman": "1.03 kB"
        },
        "dimensions": {
          "width": 10,
          "height": 15,
          "ratio": "3:2"
        },
        "processTime": [
          0,
          535476347
        ]
      },
      {
        "variantName": "sqip-legacy",
        "name": "mona-lisa-sqip-legacy.svg",
        "dist": "/Users/bene/dev/sqip/demo/public/processed/mona-lisa-sqip-legacy.svg",
        "sizes": {
          "originalBytes": 1202,
          "originalHuman": "1.2 kB",
          "gzipBytes": 761,
          "gzipHuman": "761 B",
          "brotliBytes": 749,
          "brotliHuman": "749 B"
        },
        "dimensions": {
          "width": 1200,
          "height": 1788,
          "ratio": "149:100"
        },
        "processTime": [
          3,
          226241244
        ]
      },
      {
        "variantName": "sqip",
        "name": "mona-lisa-sqip.svg",
        "dist": "/Users/bene/dev/sqip/demo/public/processed/mona-lisa-sqip.svg",
        "sizes": {
          "originalBytes": 1111,
          "originalHuman": "1.11 kB",
          "gzipBytes": 540,
          "gzipHuman": "540 B",
          "brotliBytes": 482,
          "brotliHuman": "482 B"
        },
        "dimensions": {
          "width": 300,
          "height": 447,
          "ratio": "149:100"
        },
        "processTime": [
          3,
          17129593
        ]
      },
      {
        "variantName": "sqip-pixels",
        "name": "mona-lisa-sqip-pixels.svg",
        "dist": "/Users/bene/dev/sqip/demo/public/processed/mona-lisa-sqip-pixels.svg",
        "sizes": {
          "originalBytes": 5246,
          "originalHuman": "5.25 kB",
          "gzipBytes": 955,
          "gzipHuman": "955 B",
          "brotliBytes": 623,
          "brotliHuman": "623 B"
        },
        "dimensions": {
          "width": 800,
          "height": 1200,
          "ratio": "3:2"
        },
        "processTime": [
          0,
          617748349
        ]
      },
      {
        "variantName": "sqip-art",
        "name": "mona-lisa-sqip-art.svg",
        "dist": "/Users/bene/dev/sqip/demo/public/processed/mona-lisa-sqip-art.svg",
        "sizes": {
          "originalBytes": 3356,
          "originalHuman": "3.36 kB",
          "gzipBytes": 1268,
          "gzipHuman": "1.27 kB",
          "brotliBytes": 1128,
          "brotliHuman": "1.13 kB"
        },
        "dimensions": {
          "width": 300,
          "height": 447,
          "ratio": "149:100"
        },
        "processTime": [
          8,
          349545655
        ]
      }
    ],
    "dimensions": {
      "width": 1200,
      "height": 1788,
      "ratio": "149:100"
    }
  },
  {
    "path": "/Users/bene/dev/sqip/demo/public/original/quino-al-101314-unsplash.jpg",
    "filename": "quino-al-101314-unsplash",
    "results": [
      {
        "variantName": "thumbnail",
        "name": "quino-al-101314-unsplash-thumbnail.jpg",
        "dist": "/Users/bene/dev/sqip/demo/public/processed/quino-al-101314-unsplash-thumbnail.jpg",
        "sizes": {
          "originalBytes": 16748,
          "originalHuman": "16.7 kB",
          "gzipBytes": 7647,
          "gzipHuman": "7.65 kB",
          "brotliBytes": 7566,
          "brotliHuman": "7.57 kB"
        },
        "dimensions": {
          "width": 300,
          "height": 200,
          "ratio": "3:2"
        },
        "processTime": [
          0,
          55087235
        ]
      },
      {
        "variantName": "lqip",
        "name": "quino-al-101314-unsplash-lqip.jpg",
        "dist": "/Users/bene/dev/sqip/demo/public/processed/quino-al-101314-unsplash-lqip.jpg",
        "sizes": {
          "originalBytes": 1035,
          "originalHuman": "1.03 kB",
          "gzipBytes": 631,
          "gzipHuman": "631 B",
          "brotliBytes": 608,
          "brotliHuman": "608 B"
        },
        "dimensions": {
          "width": 10,
          "height": 7,
          "ratio": "10:7"
        },
        "processTime": [
          0,
          426141778
        ]
      },
      {
        "variantName": "sqip-legacy",
        "name": "quino-al-101314-unsplash-sqip-legacy.svg",
        "dist": "/Users/bene/dev/sqip/demo/public/processed/quino-al-101314-unsplash-sqip-legacy.svg",
        "sizes": {
          "originalBytes": 1182,
          "originalHuman": "1.18 kB",
          "gzipBytes": 746,
          "gzipHuman": "746 B",
          "brotliBytes": 737,
          "brotliHuman": "737 B"
        },
        "dimensions": {
          "width": 2000,
          "height": 1333,
          "ratio": "2000:1333"
        },
        "processTime": [
          2,
          911424495
        ]
      },
      {
        "variantName": "sqip",
        "name": "quino-al-101314-unsplash-sqip.svg",
        "dist": "/Users/bene/dev/sqip/demo/public/processed/quino-al-101314-unsplash-sqip.svg",
        "sizes": {
          "originalBytes": 1067,
          "originalHuman": "1.07 kB",
          "gzipBytes": 523,
          "gzipHuman": "523 B",
          "brotliBytes": 460,
          "brotliHuman": "460 B"
        },
        "dimensions": {
          "width": 300,
          "height": 200,
          "ratio": "3:2"
        },
        "processTime": [
          3,
          103654280
        ]
      },
      {
        "variantName": "sqip-pixels",
        "name": "quino-al-101314-unsplash-sqip-pixels.svg",
        "dist": "/Users/bene/dev/sqip/demo/public/processed/quino-al-101314-unsplash-sqip-pixels.svg",
        "sizes": {
          "originalBytes": 2180,
          "originalHuman": "2.18 kB",
          "gzipBytes": 438,
          "gzipHuman": "438 B",
          "brotliBytes": 314,
          "brotliHuman": "314 B"
        },
        "dimensions": {
          "width": 800,
          "height": 500,
          "ratio": "8:5"
        },
        "processTime": [
          0,
          414290621
        ]
      },
      {
        "variantName": "sqip-art",
        "name": "quino-al-101314-unsplash-sqip-art.svg",
        "dist": "/Users/bene/dev/sqip/demo/public/processed/quino-al-101314-unsplash-sqip-art.svg",
        "sizes": {
          "originalBytes": 2860,
          "originalHuman": "2.86 kB",
          "gzipBytes": 1123,
          "gzipHuman": "1.12 kB",
          "brotliBytes": 1004,
          "brotliHuman": "1 kB"
        },
        "dimensions": {
          "width": 300,
          "height": 199,
          "ratio": "300:199"
        },
        "processTime": [
          8,
          136954385
        ]
      }
    ],
    "dimensions": {
      "width": 2000,
      "height": 1333,
      "ratio": "2000:1333"
    }
  },
  {
    "path": "/Users/bene/dev/sqip/demo/public/original/shane-young-769905-unsplash.jpg",
    "filename": "shane-young-769905-unsplash",
    "results": [
      {
        "variantName": "thumbnail",
        "name": "shane-young-769905-unsplash-thumbnail.jpg",
        "dist": "/Users/bene/dev/sqip/demo/public/processed/shane-young-769905-unsplash-thumbnail.jpg",
        "sizes": {
          "originalBytes": 22257,
          "originalHuman": "22.3 kB",
          "gzipBytes": 10093,
          "gzipHuman": "10.1 kB",
          "brotliBytes": 9980,
          "brotliHuman": "9.98 kB"
        },
        "dimensions": {
          "width": 300,
          "height": 300,
          "ratio": "1:1"
        },
        "processTime": [
          0,
          64844285
        ]
      },
      {
        "variantName": "lqip",
        "name": "shane-young-769905-unsplash-lqip.jpg",
        "dist": "/Users/bene/dev/sqip/demo/public/processed/shane-young-769905-unsplash-lqip.jpg",
        "sizes": {
          "originalBytes": 1379,
          "originalHuman": "1.38 kB",
          "gzipBytes": 897,
          "gzipHuman": "897 B",
          "brotliBytes": 881,
          "brotliHuman": "881 B"
        },
        "dimensions": {
          "width": 10,
          "height": 10,
          "ratio": "1:1"
        },
        "processTime": [
          0,
          332175116
        ]
      },
      {
        "variantName": "sqip-legacy",
        "name": "shane-young-769905-unsplash-sqip-legacy.svg",
        "dist": "/Users/bene/dev/sqip/demo/public/processed/shane-young-769905-unsplash-sqip-legacy.svg",
        "sizes": {
          "originalBytes": 1118,
          "originalHuman": "1.12 kB",
          "gzipBytes": 698,
          "gzipHuman": "698 B",
          "brotliBytes": 681,
          "brotliHuman": "681 B"
        },
        "dimensions": {
          "width": 1024,
          "height": 1024,
          "ratio": "1:1"
        },
        "processTime": [
          3,
          18385584
        ]
      },
      {
        "variantName": "sqip",
        "name": "shane-young-769905-unsplash-sqip.svg",
        "dist": "/Users/bene/dev/sqip/demo/public/processed/shane-young-769905-unsplash-sqip.svg",
        "sizes": {
          "originalBytes": 1054,
          "originalHuman": "1.05 kB",
          "gzipBytes": 535,
          "gzipHuman": "535 B",
          "brotliBytes": 473,
          "brotliHuman": "473 B"
        },
        "dimensions": {
          "width": 300,
          "height": 300,
          "ratio": "1:1"
        },
        "processTime": [
          3,
          438531764
        ]
      },
      {
        "variantName": "sqip-pixels",
        "name": "shane-young-769905-unsplash-sqip-pixels.svg",
        "dist": "/Users/bene/dev/sqip/demo/public/processed/shane-young-769905-unsplash-sqip-pixels.svg",
        "sizes": {
          "originalBytes": 3514,
          "originalHuman": "3.51 kB",
          "gzipBytes": 681,
          "gzipHuman": "681 B",
          "brotliBytes": 477,
          "brotliHuman": "477 B"
        },
        "dimensions": {
          "width": 800,
          "height": 800,
          "ratio": "1:1"
        },
        "processTime": [
          0,
          332647694
        ]
      },
      {
        "variantName": "sqip-art",
        "name": "shane-young-769905-unsplash-sqip-art.svg",
        "dist": "/Users/bene/dev/sqip/demo/public/processed/shane-young-769905-unsplash-sqip-art.svg",
        "sizes": {
          "originalBytes": 3338,
          "originalHuman": "3.34 kB",
          "gzipBytes": 1250,
          "gzipHuman": "1.25 kB",
          "brotliBytes": 1128,
          "brotliHuman": "1.13 kB"
        },
        "dimensions": {
          "width": 300,
          "height": 300,
          "ratio": "1:1"
        },
        "processTime": [
          9,
          940247032
        ]
      }
    ],
    "dimensions": {
      "width": 1024,
      "height": 1024,
      "ratio": "1:1"
    }
  }
]
